dev_email/__init__.py
dev_email/backends/__init__.py
dev_email/backends/development.py
django_dev_email-1.0.2.dist-info/DESCRIPTION.rst
django_dev_email-1.0.2.dist-info/METADATA
django_dev_email-1.0.2.dist-info/metadata.json
django_dev_email-1.0.2.dist-info/RECORD
django_dev_email-1.0.2.dist-info/top_level.txt
django_dev_email-1.0.2.dist-info/WHEEL
